Workbook

Sheet Dashboard
A1: SEPA SIGNALS — Watch List Command Center
A2: Minervini methodology • position trading • global universe
A4: SETTINGS (position-size engine reads these)
A5: Account size ($) | B5: 100000
A6: Risk per trade (%) | B6: 0.0125
A7: Risk budget / trade ($) | B7: =B5*B6 -> 1250 | C7: ← drives Shares column on every watch list
A8: Buy-zone width (%) | B8: 0.05
A10: MARKET TONE (global gate — third conviction axis)
A11: Current read: | B11: Confirmed uptrend
A12: Rule: | B12: In a Correction / Under Pressure tape, downgrade every setup one tier. No new buys in a Correction.
A15: THE LADDER (a stock moves up rungs as all 3 axes align — or falls off)
A16: WATCH | B16: Underline. Shows potential, base NOT mature. On the radar.
A17: BUY ALERT | B17: Setup maturing. Fundamentals + technicals lining up. Watch closely.
A18: BUY READY | B18: Circled asterisk (*). Pivot formed & immediately buyable, price in buy zone.
A19: POSITIONS | B19: Owned. Manage follow-through vs squat; trail the 20/50-day.
A20: RESET WATCH | B20: Stopped out. Hold for a failure reset (base failure / pivot failure reset).
A23: MINERVINI NOTATION (use in the flag columns)
A24: Column | B24: Mark | C24: Meaning
A25: Conv (circle) | B25: Y | C25: “I really like it” — highest conviction.
A26: Pivot* (asterisk) | B26: Y | C26: A pivot point has formed.
A27: Buyable (circled *) | B27: Y | C27: Pivot is immediately buyable — actionable now.
A28: pb | B28: Y | C28: Interested on a pullback (different entry path).
A31: SETUP PLAYBOOK (sourced thresholds — the Footprint / Setup columns)
A32: Setup | B32: Defining structure | D32: Key thresholds | E32: Entry trigger
A33: VCP / 3C | B33: Series of contractions, each shallower; volume dries up into the pivot. | D33: Footprint = [wks]W [1st%]/[last%] [n]T. Final contraction tight (~3-5%). | E33: Break above pivot (last contraction high) on volume surge.
A34: Cup-with-handle | B34: Rounded base; handle = final shallow contraction under the rim. | D34: Handle drifts down/sideways, low volume; handle high ≈ pivot. | E34: Break above handle high on volume expansion.
A35: Cheat (4-phase) | B35: A→Downtrend, B→Uptrend, C→Pause/plateau, D→Breakout. | D35: Correction 7-25 wks, 15-40% deep (≤60%). Plateau 5-10%, ideally a shakeout. | E35: Take out the high of the plateau (the cheat / handle).
A36: Livermore PP | B36: Downtrend breaks, then TWO reactionary pullbacks. | D36: PP set by the trend change; wait for confirmed penetration. | E36: Buy above the 2nd reaction high (confirmation).
A37: Power Play | B37: Explosive thrust then tight high flag. Velocity pattern. | D37: +100% in <8 wks after dormancy; flag ≤20-25% over 3-6 wks (min ~12 days); volume contracts hard just before breakout. | E37: Break above tight-flag high; bypasses extension filters.
A38: Primary base | B38: First proper base after a Stage-2 turn. | D38: Standard Trend Template must hold (8/8 ideal). | E38: Break above base pivot on volume.
A41: CONVICTION MODEL
A42: Three independent axes — score each separately, buy only when they ALIGN: 1) FUNDAMENTAL — EPS/sales acceleration, margin trend, ROE. 2) TECHNICAL — Stage 2, Trend Template, a valid setup above. 3) MARKET — healthy tape (the gate above). “A good company is not always a good stock.” Fundamentally sound ≠ price-ready — be patient and wait for the setup.

Sheet Watch
A1: Watch — radar / not mature
A3: Ticker | B3: Company | C3: Exch | D3: Sector | E3: Business summary | F3: Stage | G3: TT /8 | H3: RS | I3: Fund | J3: Setup | K3: Footprint | L3: Conv | M3: Pivot* | N3: Buyable | O3: pb | P3: Pivot $ | Q3: Buy-zone top | R3: Entry $ | S3: Stop $ | T3: Stop % | U3: Shares | V3: Added | W3: Reviewed | X3: Notes
A4: FFEXT | B4: Fortis Extended | C4: US | D4: Retail | E4: Retail name — synthetic demo data | F4: 2 - Advance | G4: 8 | H4: 84 | I4: EPS↑+Sales↑+ROE>17 | J4: — | K4: — | L4: Y | Q4: =IF(P4="","",P4*(1+Dashboard!$B$8)) | T4: =IF(OR(R4="",S4="",R4=0),"",(R4-S4)/R4) | U4: =IF(OR(R4="",S4="",R4=S4),"",ROUND(Dashboard!$B$7/(R4-S4),0)) | V4: 2026-05-25 | W4: 46167 | X4: [NEW] stage2 TT8/8 RS84 fund✓ no setup
A5: GGEXT | B5: Granite Growth | C5: US | D5: Consumer | E5: Consumer name — synthetic demo data | F5: 2 - Advance | G5: 8 | H5: 99 | I5: EPS↑+Sales↑+ROE>17 | J5: — | K5: — | L5: Y | Q5: =IF(P5="","",P5*(1+Dashboard!$B$8)) | T5: =IF(OR(R5="",S5="",R5=0),"",(R5-S5)/R5) | U5: =IF(OR(R5="",S5="",R5=S5),"",ROUND(Dashboard!$B$7/(R5-S5),0)) | V5: 2026-05-25 | W5: 46167 | X5: [NEW] stage2 TT8/8 RS99 fund✓ no setup
A6: NNEXT | B6: Nimbus Networks | C6: US | D6: Telecom | E6: Telecom name — synthetic demo data | F6: 2 - Advance | G6: 8 | H6: 74 | I6: EPS↑+Sales↑ | J6: — | K6: — | L6: Y | Q6: =IF(P6="","",P6*(1+Dashboard!$B$8)) | T6: =IF(OR(R6="",S6="",R6=0),"",(R6-S6)/R6) | U6: =IF(OR(R6="",S6="",R6=S6),"",ROUND(Dashboard!$B$7/(R6-S6),0)) | V6: 2026-05-25 | W6: 46167 | X6: [NEW] stage2 TT8/8 RS74 fund✓ no setup

Sheet Buy Alert
A1: Buy Alert — setup maturing
A3: Ticker | B3: Company | C3: Exch | D3: Sector | E3: Business summary | F3: Stage | G3: TT /8 | H3: RS | I3: Fund | J3: Setup | K3: Footprint | L3: Conv | M3: Pivot* | N3: Buyable | O3: pb | P3: Pivot $ | Q3: Buy-zone top | R3: Entry $ | S3: Stop $ | T3: Stop % | U3: Shares | V3: Added | W3: Reviewed | X3: Notes
A4: BBVCP | B4: Bluefin Biotech | C4: US | D4: Biotech | E4: Biotech name — synthetic demo data | F4: 2 - Advance | G4: 8 | H4: 70 | I4: EPS↑+Sales↑+ROE>17 | J4: VCP / 3C | K4: 13W 16/4 4T | L4: Y | M4: Y | P4: 26.54 | Q4: =IF(P4="","",P4*(1+Dashboard!$B$8)) -> 27.867 | R4: 26.54 | S4: 23.43 | T4: =IF(OR(R4="",S4="",R4=0),"",(R4-S4)/R4) -> 0.11718161 | U4: =IF(OR(R4="",S4="",R4=S4),"",ROUND(Dashboard!$B$7/(R4-S4),0)) -> 402 | V4: 2026-05-25 | W4: 46167 | X4: [NEW] stage2 TT8/8 RS70 fund✓ VCP / 3C

Sheet Buy Ready
A1: Buy Ready — actionable now
A3: Ticker | B3: Company | C3: Exch | D3: Sector | E3: Business summary | F3: Stage | G3: TT /8 | H3: RS | I3: Fund | J3: Setup | K3: Footprint | L3: Conv | M3: Pivot* | N3: Buyable | O3: pb | P3: Pivot $ | Q3: Buy-zone top | R3: Entry $ | S3: Stop $ | T3: Stop % | U3: Shares | V3: Added | W3: Reviewed | X3: Notes
A4: AAVCP | B4: Apex Velocity Corp | C4: US | D4: Software | E4: Software name — synthetic demo data | F4: 2 - Advance | G4: 8 | H4: 79 | I4: EPS↑+Sales↑+ROE>17 | J4: VCP / 3C | K4: 13W 13/4 4T | L4: Y | M4: Y | N4: Y | P4: 37.88 | Q4: =IF(P4="","",P4*(1+Dashboard!$B$8)) -> 39.774 | R4: 37.88 | S4: 34.51 | T4: =IF(OR(R4="",S4="",R4=0),"",(R4-S4)/R4) -> 0.088965153 | U4: =IF(OR(R4="",S4="",R4=S4),"",ROUND(Dashboard!$B$7/(R4-S4),0)) -> 371 | V4: 2026-05-25 | W4: 46167 | X4: [NEW] stage2 TT8/8 RS79 fund✓ VCP / 3C(buyable)
A5: DDPOW | B5: Delta Dynamics | C5: US | D5: Semis | E5: Semis name — synthetic demo data | F5: 2 - Advance | G5: 8 | H5: 89 | I5: EPS↑+Sales↑+ROE>17 | J5: Power Play | K5: +114%/40d flag 10d | L5: Y | M5: Y | N5: Y | P5: 16.44 | Q5: =IF(P5="","",P5*(1+Dashboard!$B$8)) -> 17.262 | R5: 16.44 | S5: 14.87 | T5: =IF(OR(R5="",S5="",R5=0),"",(R5-S5)/R5) -> 0.095498783 | U5: =IF(OR(R5="",S5="",R5=S5),"",ROUND(Dashboard!$B$7/(R5-S5),0)) -> 796 | V5: 2026-05-25 | W5: 46167 | X5: [NEW] POWER PLAY RS89 fund✓ +114%/40d flag 10d
A6: EEPOW | B6: Echo Energy | C6: US | D6: Energy | E6: Energy name — synthetic demo data | F6: 2 - Advance | G6: 8 | H6: 94 | I6: EPS↑+Sales↑ | J6: Power Play | K6: +114%/40d flag 10d | L6: Y | M6: Y | N6: Y | P6: 17.58 | Q6: =IF(P6="","",P6*(1+Dashboard!$B$8)) -> 18.459 | R6: 17.58 | S6: 15.9 | T6: =IF(OR(R6="",S6="",R6=0),"",(R6-S6)/R6) -> 0.09556314 | U6: =IF(OR(R6="",S6="",R6=S6),"",ROUND(Dashboard!$B$7/(R6-S6),0)) -> 744 | V6: 2026-05-25 | W6: 46167 | X6: [NEW] POWER PLAY RS94 fund✓ +114%/40d flag 10d

Sheet Positions
A1: POSITIONS — open trades & exit management
A3: Ticker | B3: Company | C3: Setup | D3: Entry date | E3: Entry $ | F3: Shares | G3: Stop $ | H3: Current $ | I3: Init risk $ | J3: Open P/L $ | K3: Current R | L3: Status | M3: Trail ref | N3: Notes
A4: ARNA | B4: Arena Pharmaceuticals | C4: Cheat | D4: 41081 | E4: 8.1 | F4: 600 | G4: 7.45 | H4: 9.2 | I4: =IF(OR(E4="",G4="",F4=""),"",(E4-G4)*F4) -> 390 | J4: =IF(OR(H4="",E4="",F4=""),"",(H4-E4)*F4) -> 660 | K4: =IF(OR(H4="",E4="",G4="",E4=G4),"",(H4-E4)/(E4-G4)) -> 1.6923077 | L4: Follow-through OK | M4: 20-day | N4: EXAMPLE — close-based stop; trail 20-day on a runner
I5: =IF(OR(E5="",G5="",F5=""),"",(E5-G5)*F5) | J5: =IF(OR(H5="",E5="",F5=""),"",(H5-E5)*F5) | K5: =IF(OR(H5="",E5="",G5="",E5=G5),"",(H5-E5)/(E5-G5))
I6: =IF(OR(E6="",G6="",F6=""),"",(E6-G6)*F6) | J6: =IF(OR(H6="",E6="",F6=""),"",(H6-E6)*F6) | K6: =IF(OR(H6="",E6="",G6="",E6=G6),"",(H6-E6)/(E6-G6))
I7: =IF(OR(E7="",G7="",F7=""),"",(E7-G7)*F7) | J7: =IF(OR(H7="",E7="",F7=""),"",(H7-E7)*F7) | K7: =IF(OR(H7="",E7="",G7="",E7=G7),"",(H7-E7)/(E7-G7))
I8: =IF(OR(E8="",G8="",F8=""),"",(E8-G8)*F8) | J8: =IF(OR(H8="",E8="",F8=""),"",(H8-E8)*F8) | K8: =IF(OR(H8="",E8="",G8="",E8=G8),"",(H8-E8)/(E8-G8))
I9: =IF(OR(E9="",G9="",F9=""),"",(E9-G9)*F9) | J9: =IF(OR(H9="",E9="",F9=""),"",(H9-E9)*F9) | K9: =IF(OR(H9="",E9="",G9="",E9=G9),"",(H9-E9)/(E9-G9))
I10: =IF(OR(E10="",G10="",F10=""),"",(E10-G10)*F10) | J10: =IF(OR(H10="",E10="",F10=""),"",(H10-E10)*F10) | K10: =IF(OR(H10="",E10="",G10="",E10=G10),"",(H10-E10)/(E10-G10))
I11: =IF(OR(E11="",G11="",F11=""),"",(E11-G11)*F11) | J11: =IF(OR(H11="",E11="",F11=""),"",(H11-E11)*F11) | K11: =IF(OR(H11="",E11="",G11="",E11=G11),"",(H11-E11)/(E11-G11))
I12: =IF(OR(E12="",G12="",F12=""),"",(E12-G12)*F12) | J12: =IF(OR(H12="",E12="",F12=""),"",(H12-E12)*F12) | K12: =IF(OR(H12="",E12="",G12="",E12=G12),"",(H12-E12)/(E12-G12))
I13: =IF(OR(E13="",G13="",F13=""),"",(E13-G13)*F13) | J13: =IF(OR(H13="",E13="",F13=""),"",(H13-E13)*F13) | K13: =IF(OR(H13="",E13="",G13="",E13=G13),"",(H13-E13)/(E13-G13))
I14: =IF(OR(E14="",G14="",F14=""),"",(E14-G14)*F14) | J14: =IF(OR(H14="",E14="",F14=""),"",(H14-E14)*F14) | K14: =IF(OR(H14="",E14="",G14="",E14=G14),"",(H14-E14)/(E14-G14))
I15: =IF(OR(E15="",G15="",F15=""),"",(E15-G15)*F15) | J15: =IF(OR(H15="",E15="",F15=""),"",(H15-E15)*F15) | K15: =IF(OR(H15="",E15="",G15="",E15=G15),"",(H15-E15)/(E15-G15))
I16: =IF(OR(E16="",G16="",F16=""),"",(E16-G16)*F16) | J16: =IF(OR(H16="",E16="",F16=""),"",(H16-E16)*F16) | K16: =IF(OR(H16="",E16="",G16="",E16=G16),"",(H16-E16)/(E16-G16))
... I19: =IF(OR(E19="",G19="",F19=""),"",(E19-G19)*F19) | J19: =IF(OR(H19="",E19="",F19=""),"",(H19-E19)*F19) | K19: =IF(OR(H19="",E19="",G19="",E19=G19),"",(H19-E19)/(E19-G19))

Sheet Reset Watch
A1: RESET WATCH — stopped out, monitoring for a failure reset
A3: Ticker | B3: Company | C3: Failed setup | D3: Stopped date | E3: Loss (R) | F3: Reset type expected | G3: Days since | H3: Reset status | I3: New pivot $ | J3: Notes
A4: XYZ | B4: Example Co | C4: VCP / 3C | D4: 46154 | E4: -1 | F4: Pivot failure reset (days) | G4: =IF(D4="","",TODAY()-D4) -> 13 | H4: Watching | J4: EXAMPLE — shaken out, not soured; keep on radar for a tighter 2nd setup
G5: =IF(D5="","",TODAY()-D5)
G6: =IF(D6="","",TODAY()-D6)
G7: =IF(D7="","",TODAY()-D7)
G8: =IF(D8="","",TODAY()-D8)
G9: =IF(D9="","",TODAY()-D9)
G10: =IF(D10="","",TODAY()-D10)
G11: =IF(D11="","",TODAY()-D11)
G12: =IF(D12="","",TODAY()-D12)
G13: =IF(D13="","",TODAY()-D13)
G14: =IF(D14="","",TODAY()-D14)
G15: =IF(D15="","",TODAY()-D15)
G16: =IF(D16="","",TODAY()-D16)
... G19: =IF(D19="","",TODAY()-D19)
